sdv/__init__.py
sdv/_utils.py
sdv/errors.py
sdv/cag/__init__.py
sdv/cag/_errors.py
sdv/cag/_utils.py
sdv/cag/base.py
sdv/cag/fixed_combinations.py
sdv/cag/fixed_increments.py
sdv/cag/inequality.py
sdv/cag/one_hot_encoding.py
sdv/cag/programmable_constraint.py
sdv/cag/range.py
sdv/constraints/__init__.py
sdv/constraints/base.py
sdv/constraints/errors.py
sdv/constraints/tabular.py
sdv/constraints/utils.py
sdv/data_processing/__init__.py
sdv/data_processing/data_processor.py
sdv/data_processing/datetime_formatter.py
sdv/data_processing/errors.py
sdv/data_processing/numerical_formatter.py
sdv/data_processing/utils.py
sdv/datasets/__init__.py
sdv/datasets/demo.py
sdv/datasets/local.py
sdv/evaluation/__init__.py
sdv/evaluation/_utils.py
sdv/evaluation/multi_table.py
sdv/evaluation/single_table.py
sdv/io/__init__.py
sdv/io/local/__init__.py
sdv/io/local/local.py
sdv/lite/__init__.py
sdv/lite/single_table.py
sdv/logging/__init__.py
sdv/logging/logger.py
sdv/logging/sdv_logger_config.yml
sdv/logging/utils.py
sdv/metadata/__init__.py
sdv/metadata/errors.py
sdv/metadata/metadata.py
sdv/metadata/metadata_upgrader.py
sdv/metadata/multi_table.py
sdv/metadata/single_table.py
sdv/metadata/utils.py
sdv/metadata/visualization.py
sdv/metrics/__init__.py
sdv/metrics/demos.py
sdv/metrics/relational.py
sdv/metrics/tabular.py
sdv/metrics/timeseries.py
sdv/multi_table/__init__.py
sdv/multi_table/base.py
sdv/multi_table/dayz.py
sdv/multi_table/hma.py
sdv/multi_table/utils.py
sdv/sampling/__init__.py
sdv/sampling/hierarchical_sampler.py
sdv/sampling/independent_sampler.py
sdv/sampling/tabular.py
sdv/sequential/__init__.py
sdv/sequential/par.py
sdv/single_table/__init__.py
sdv/single_table/base.py
sdv/single_table/copulagan.py
sdv/single_table/copulas.py
sdv/single_table/ctgan.py
sdv/single_table/dayz.py
sdv/single_table/utils.py
sdv/utils/__init__.py
sdv/utils/mixins.py
sdv/utils/poc.py
sdv/utils/utils.py
sdv/version/__init__.py
sdv-1.33.0.dist-info/licenses/LICENSE
sdv-1.33.0.dist-info/METADATA
sdv-1.33.0.dist-info/WHEEL
sdv-1.33.0.dist-info/entry_points.txt
sdv-1.33.0.dist-info/top_level.txt
sdv-1.33.0.dist-info/RECORD
